[
  {
    "name": "Бэби Формула Мишки Кальций жевательные пастилки, 30 шт.",
    "producer": "Эвалар, Россия",
    "active_component": "Поливитамины, Минералы",
    "qrcode": [
      4602242008934
    ],
    "url": "https://www.eapteka.ru/goods/id270466/"
  },
  {
    "name": "Проктонис капсулы 0,27 г, 60 шт.",
    "producer": "ВИС ООО, Россия",
    "active_component": "",
    "qrcode": [
      4607039975413
    ],
    "url": "https://www.eapteka.ru/goods/id215418/"
  },
  {
    "name": "Золотой конек, таблетки 650 мг, 20 шт.",
    "producer": "Иконг Фармацевтикал, Индонезия",
    "active_component": "",
    "qrcode": [
      8995152900433
    ],
    "url": "https://www.eapteka.ru/goods/id217974/"
  },
  {
    "name": "Витрум Пренатал Плюс таблетки, 30 шт.",
    "producer": "Eagle Nutritionals,Inc., США",
    "active_component": "Поливитамины, Минералы",
    "qrcode": [
      7038319109124
    ],
    "url": "https://www.eapteka.ru/goods/id299972/"
  },
  {
    "name": "Омега Fit Omega 3-6-9, капсулы 90 шт.",
    "producer": "Академия Т, Россия",
    "active_component": "",
    "qrcode": [
      4607055681541
    ],
    "url": "https://www.eapteka.ru/goods/id244720/"
  },
  {
    "name": "Окулист, капсулы, 60 шт.",
    "producer": "Диод, Россия",
    "active_component": "",
    "qrcode": [
      4607001340270
    ],
    "url": "https://www.eapteka.ru/goods/id208246/"
  },
  {
    "name": "Гинкго Билоба Форте, таблетки, 60 шт.",
    "producer": "Авен ООО, Россия",
    "active_component": "",
    "qrcode": [
      4612730760329
    ],
    "url": "https://www.eapteka.ru/goods/id224578/"
  },
  {
    "name": "Гарде 150 капсулы 0,23 г, 30 шт.",
    "producer": "Фармакор Продакшн, Россия",
    "active_component": "",
    "qrcode": [
      4603569722800
    ],
    "url": "https://www.eapteka.ru/goods/id495328/"
  },
  {
    "name": "Фулфлекс капсулы, 24 шт.",
    "producer": "ВИС ООО, Россия",
    "active_component": "",
    "qrcode": [
      4607039975246
    ],
    "url": "https://www.eapteka.ru/goods/id210034/"
  },
  {
    "name": "Ярса Гумба Форте таблетки 1,5 г, 5 шт.",
    "producer": "Растительные Ресурсы НПК, Россия",
    "active_component": "",
    "qrcode": [
      4610007620239
    ],
    "url": "https://www.eapteka.ru/goods/id266700/"
  },
  {
    "name": "Алфавит для мужчин, таблетки, 60 шт.",
    "producer": "ВТФ ООО, Россия",
    "active_component": "",
    "qrcode": [
      4660014181643,
      4660014181254,
      4660014182091
    ],
    "url": "https://www.eapteka.ru/goods/id213482/"
  },
  {
    "name": "Магне B6 таблетки покрыт.об., 60 шт.",
    "producer": "Хиноин Завод Фармацевтических и Химических пр-тов, Венгрия",
    "active_component": "Магний, Пиридоксин",
    "qrcode": [
      3582910094975
    ],
    "url": "https://www.eapteka.ru/goods/id311687/"
  },
  {
    "name": "БиоТоффи Пробиотик шоколадный батончик, 5г 10 шт.",
    "producer": "KRAS prehrambena industrija d. d., Хорватия",
    "active_component": "",
    "qrcode": [
      4607013581593
    ],
    "url": "https://www.eapteka.ru/goods/id507243/"
  },
  {
    "name": "Проглицин капсулы, 90 шт.",
    "producer": "Глобал Хэлфкеар ООО, Россия",
    "active_component": "",
    "qrcode": [
      4640033071545
    ],
    "url": "https://www.eapteka.ru/goods/id501906/"
  },
  {
    "name": "Селен+Цинк Эвалар капсулы по 0,75 мг, 60 шт",
    "producer": "Эвалар, Россия",
    "active_component": "",
    "qrcode": [
      4602242025290
    ],
    "url": "https://www.eapteka.ru/goods/id514824/"
  },
  {
    "name": "Фруттилар Витамин D3 2000 МЕ пастилки в форме мармеладных ягод, 30 шт.",
    "producer": "Эвалар, Россия",
    "active_component": "",
    "qrcode": [
      4602242024248
    ],
    "url": "https://www.eapteka.ru/goods/id512852/"
  },
  {
    "name": "Кардиотон таблетки покрыт.об. 505 мг, 60 шт.",
    "producer": "Парафарм, Россия",
    "active_component": "",
    "qrcode": [
      4605920000572
    ],
    "url": "https://www.eapteka.ru/goods/id498520/"
  },
  {
    "name": "Мультивитамины 12+9 капсулы, 60 шт.",
    "producer": "Глобал Хэлфкеар ООО, Россия",
    "active_component": "",
    "qrcode": [
      4640033071569
    ],
    "url": "https://www.eapteka.ru/goods/id501905/"
  },
  {
    "name": "Доппельгерц Kinder Глицин+Витамины для детей с 3-х лет со вкусом апельсина жевательные таблетки, 60 шт.",
    "producer": "Квайссер Фарма, Германия",
    "active_component": "",
    "qrcode": [
      4009932557251
    ],
    "url": "https://www.eapteka.ru/goods/id486405/"
  },
  {
    "name": "Хондроитин Усиленная формула капсулы 60 шт., упак.",
    "producer": "Реалкапс, Россия",
    "active_component": "",
    "qrcode": [
      4607136740440
    ],
    "url": "https://www.eapteka.ru/goods/id250317/"
  }
]