[
  {
    "name": "Orihiro Витамин С со вкусом лимона таблетки, 120 шт.",
    "producer": "Орихиро, Япония",
    "active_component": "",
    "qrcode": [
      4571157256740
    ],
    "url": "https://www.eapteka.ru/goods/id330733/"
  },
  {
    "name": "Плантиокс, таблетки 500 мг, 120 шт.",
    "producer": "Ханкинтатукку, Финляндия",
    "active_component": "",
    "qrcode": [
      6428300091353
    ],
    "url": "https://www.eapteka.ru/goods/id211324/"
  },
  {
    "name": "Грибная серия Кордицепс с Мумие капсулы, 60 шт.",
    "producer": "Алфит Плюс ООО, Россия",
    "active_component": "",
    "qrcode": [
      7930096130080
    ],
    "url": "https://www.eapteka.ru/goods/id512226/"
  },
  {
    "name": "UltraBalance Omega-3 Premium/Омега 3 рыбий жир высокой концентрации 1620 мг капсулы, 90 шт.",
    "producer": "Сибфармконтракт, Россия",
    "active_component": "",
    "qrcode": [
      2002174455004
    ],
    "url": "https://www.eapteka.ru/goods/id514046/"
  },
  {
    "name": "Гепагард Актив капсулы 360 мг, 120 шт.",
    "producer": "Биос НПФ, Россия",
    "active_component": "",
    "qrcode": [
      4630009622475
    ],
    "url": "https://www.eapteka.ru/goods/id221378/"
  },
  {
    "name": "Солгар Витамин С, с малиновым вкусом 500 мг таблетки 90 шт.",
    "producer": "Solgar Vitamin and Herb, США",
    "active_component": "",
    "qrcode": [
      33984004085,
      33984004085
    ],
    "url": "https://www.eapteka.ru/goods/id216677/"
  },
  {
    "name": "Мильгамма композитум таблетки покрыт.об.100 мг+100 мг, 60 шт.",
    "producer": "Мауэрманн-Арцнаймиттель КГ, Германия",
    "active_component": "Бенфотиамин, Пиридоксин",
    "qrcode": [
      4030674003195
    ],
    "url": "https://www.eapteka.ru/goods/id25773/"
  },
  {
    "name": "Нэйчес Баунти L- Аргинин, капсулы 1000 мг 50 шт.",
    "producer": "Nature’s Bounty Inc, США",
    "active_component": "",
    "qrcode": [
      74312077609,
      74312077609
    ],
    "url": "https://www.eapteka.ru/goods/id237706/"
  },
  {
    "name": "Простатон таблетки покрыт.об. 500 мг, 60 шт.",
    "producer": "Парафарм, Россия",
    "active_component": "",
    "qrcode": [
      4605920001524
    ],
    "url": "https://www.eapteka.ru/goods/id498527/"
  },
  {
    "name": "Биолит Биота комплекс Biota N1 капсулы 50 шт.+ Biota N2 капсулы 50 шт, уп.",
    "producer": "Биолит, Россия",
    "active_component": "",
    "qrcode": [
      1705770207893
    ],
    "url": "https://www.eapteka.ru/goods/id482940/"
  },
  {
    "name": "Флорадикс Айронвиталь, флакон 250 мл",
    "producer": "Салюс-Хаус ГмбХ, Германия",
    "active_component": "",
    "qrcode": [
      4004148017179
    ],
    "url": "https://www.eapteka.ru/goods/id228772/"
  },
  {
    "name": "Astrum Zym-Complex Ферменты и антиоксиданты, 60 табл",
    "producer": "Ворлд Вайд Нутрацевтикал Инк, США",
    "active_component": "",
    "qrcode": [
      "7 57807 99521",
      75780799521,
      757807995212,
      757807995212
    ],
    "url": "https://www.eapteka.ru/goods/id238457/"
  },
  {
    "name": "Хонда МСМ Эвалар таблетки, 60 шт.",
    "producer": "Эвалар, Россия",
    "active_component": "",
    "qrcode": [
      4602242021452
    ],
    "url": "https://www.eapteka.ru/goods/id483055/"
  },
  {
    "name": "Магне B6 таблетки покрыт.об., 180 шт.",
    "producer": "Хиноин Завод Фармацевтических и Химических пр-тов, Венгрия",
    "active_component": "Магний, Пиридоксин",
    "qrcode": [
      3664798037401
    ],
    "url": "https://www.eapteka.ru/goods/id511098/"
  },
  {
    "name": "Lactoflorene Холестерол пакетики, 20 шт.",
    "producer": "S.I.I.T. s.r.l., Италия",
    "active_component": "",
    "qrcode": [
      8004995458749
    ],
    "url": "https://www.eapteka.ru/goods/id327750/"
  },
  {
    "name": "Lactoflorene Плоский живот пакетики, 20 шт.",
    "producer": "S.I.I.T. s.r.l., Италия",
    "active_component": "",
    "qrcode": [
      8004995458770
    ],
    "url": "https://www.eapteka.ru/goods/id327749/"
  },
  {
    "name": "Солгар Суперконцентрат изофлавонов, таблетки, 30 шт.",
    "producer": "Solgar Vitamin and Herb, США",
    "active_component": "",
    "qrcode": [
      33984014787,
      33984014787
    ],
    "url": "https://www.eapteka.ru/goods/id216694/"
  },
  {
    "name": "Комплекс 5-НТР Эвалар капсулы по 0,4 г, 60 шт",
    "producer": "Эвалар, Россия",
    "active_component": "",
    "qrcode": [
      4602242024545
    ],
    "url": "https://www.eapteka.ru/goods/id514822/"
  },
  {
    "name": "Пантопровит капсулы, 60 шт.",
    "producer": "Merz Pharmaceuticals GmbH, Германия",
    "active_component": "",
    "qrcode": [
      4046222752484
    ],
    "url": "https://www.eapteka.ru/goods/id506511/"
  },
  {
    "name": "Нэйчес Баунти Кожа, волосы, ногти, капсулы 60 шт",
    "producer": "Nature’s Bounty Inc, США",
    "active_component": "",
    "qrcode": [
      74312075803,
      74312075803
    ],
    "url": "https://www.eapteka.ru/goods/id237704/"
  }
]